miu_mono/__init__.py
miu_mono/cli.py
miu_mono-2.0.0.dist-info/METADATA
miu_mono-2.0.0.dist-info/WHEEL
miu_mono-2.0.0.dist-info/entry_points.txt
miu_mono-2.0.0.dist-info/RECORD
