Metadata-Version: 2.4
Name: miu-mono
Version: 2.0.0
Summary: AI Agent Framework - batteries included
License: MIT
Requires-Python: >=3.11
Requires-Dist: asyncclick>=8.0
Requires-Dist: miu-code
Requires-Dist: miu-core[all]
Provides-Extra: all
Requires-Dist: miu-examples; extra == 'all'
Requires-Dist: miu-studio; extra == 'all'
Provides-Extra: examples
Requires-Dist: miu-examples; extra == 'examples'
Provides-Extra: studio
Requires-Dist: miu-studio; extra == 'studio'
